<?xml version="1.0" encoding="UTF-8"?><magicdraw><class classType="Class" humanType="Class" icon="ClinicalProfiles_files/icon_class_1827212229.jpg" id="_18_2_bf902f3_1528990624065_529626_4957"><allGeneralClassifiers humanName="All General Classifiers"><class classType="Class" humanType="Class" icon="ClinicalProfiles_files/icon_class_1827212229.jpg" name="Distribution" refid="_18_2_bf902f3_1528990751323_154132_5071"/></allGeneralClassifiers><generalization humanName="Generalization"><generalization classType="Generalization" humanType="Generalization" icon="ClinicalProfiles_files/icon_generalization_413550077.jpg" isRelationship="true" refid="_18_2_bf902f3_1528991551007_300513_5352"/></generalization><inheritedMember humanName="Inherited Member"><property classType="Property" humanType="Property" icon="ClinicalProfiles_files/icon_property_1181887497.jpg" name=" : Distribution Algorithm" refid="_18_2_bf902f3_1528991739584_505560_5458"/><property classType="Property" humanType="Property" icon="ClinicalProfiles_files/icon_property_1181887497.jpg" name="type for" refid="_18_2_bf902f3_1528990769589_824789_5111"/></inheritedMember><isAbstract humanName="Is Abstract" mode="standard,expert">false</isAbstract><isActive humanName="Is Active" mode="standard,expert">false</isActive><isFinalSpecialization humanName="Is Final Specialization" mode="expert">false</isFinalSpecialization><isLeaf humanName="Is Leaf" mode="expert">false</isLeaf><member humanName="Member"><property classType="Property" humanType="Property" icon="ClinicalProfiles_files/icon_property_1181887497.jpg" name=" : Distribution Algorithm" refid="_18_2_bf902f3_1528991739584_505560_5458"/><property classType="Property" humanType="Property" icon="ClinicalProfiles_files/icon_property_1181887497.jpg" name="type for" refid="_18_2_bf902f3_1528990769589_824789_5111"/></member><name humanName="Name" mode="standard,expert">Boolean</name><namespace classType="Model" humanName="Namespace" humanType="Model" icon="ClinicalProfiles_files/icon_model_1260127127.jpg" name="Data" refid="eee_1045467100313_135436_1"/><ownedElement humanName="Owned Element"><generalization classType="Generalization" humanType="Generalization" icon="ClinicalProfiles_files/icon_generalization_413550077.jpg" isRelationship="true" refid="_18_2_bf902f3_1528991551007_300513_5352"/></ownedElement><owner classType="Model" humanName="Owner" humanType="Model" icon="ClinicalProfiles_files/icon_model_1260127127.jpg" mode="standard,expert" name="Data" refid="eee_1045467100313_135436_1"/><owningPackage classType="Model" humanName="Owning Package" humanType="Model" icon="ClinicalProfiles_files/icon_model_1260127127.jpg" name="Data" refid="eee_1045467100313_135436_1"/><package classType="Model" humanName="Package" humanType="Model" icon="ClinicalProfiles_files/icon_model_1260127127.jpg" name="Data" refid="eee_1045467100313_135436_1"/><qualifiedName humanName="Qualified Name" mode="expert">Boolean</qualifiedName><superClass humanName="Super Class"><class classType="Class" humanType="Class" icon="ClinicalProfiles_files/icon_class_1827212229.jpg" name="Distribution" refid="_18_2_bf902f3_1528990751323_154132_5071"/></superClass><TO_DO humanName="To Do" mode="standard,expert"/><visibility humanName="Visibility" mode="expert">public</visibility><appearsIn><diagram classType="Diagram" humanType="Diagram" icon="ClinicalProfiles_files/icon_Class Diagram_1833691024.jpg" name="Query Profile" refid="_18_2_bf902f3_1528987528298_387902_3989"/></appearsIn></class></magicdraw>